[
    {
        "date": "12/11/2022",
        "totalPrice": 703277,
        "status": false,
        "orderNumber": "NIKE-1",
        "UserId": 1,
        "StoreId": 1
    },
    {
        "date": "11/8/2022",
        "totalPrice": 245202,
        "status": false,
        "orderNumber": "Converse-2",
        "UserId": 2,
        "StoreId": 2
    },
    {
        "date": "2/13/2022",
        "totalPrice": 463483,
        "status": false,
        "orderNumber": "Vans-4",
        "UserId": 3,
        "StoreId": 3
    }
]